{
  "campaign": {
    "id": "78226932-7fe7-4e75-b458-3282ac5005d0",
    "name": "The-Celestial-Bureaucracy",
    "description": "Mock expansion of the-celestial-bureaucracy.md",
    "genre": "Fantasy",
    "difficulty_level": "medium",
    "campaign_length": "full",
    "tone": "epic",
    "setting_details": {},
    "thematic_elements": {
      "mainThemes": [],
      "keyLocations": [],
      "importantNPCs": [],
      "recurringMotifs": []
    }
  },
  "worlds": [
    {
      "id": "c441d33a-abc9-4a4b-9b3c-f0ca7625f8b5",
      "campaign_id": "mock-id",
      "name": "Mock World",
      "description": "Generated during dry run",
      "climate_type": "temperate",
      "magic_level": "standard",
      "technology_level": "medieval"
    }
  ],
  "npcs": [
    {
      "id": "bb57308c-c02f-42c3-9557-79df8fee821a",
      "world_id": "mock-world-id",
      "name": "Mock NPC",
      "race": "Human",
      "class_": "Fighter",
      "level": 5,
      "description": "Generated NPC",
      "personality": "Brave",
      "stats": {}
    }
  ],
  "quests": [
    {
      "id": "a75d1439-b607-4559-9859-c9f55d23a5e3",
      "campaign_id": "mock-id",
      "title": "Mock Quest",
      "description": "Sample quest",
      "difficulty": "medium",
      "quest_type": "main",
      "prerequisites": {},
      "rewards": {}
    }
  ],
  "locations": [
    {
      "id": "d24b1ad3-0c49-4720-9a9e-4b4ca9b37d77",
      "world_id": "mock-world-id",
      "name": "Mock Location",
      "location_type": "village",
      "description": "Sample location",
      "parent_location_id": null,
      "coordinates": null
    }
  ],
  "factions": [],
  "history_events": [],
  "memories": []
}