{
  "campaign": {
    "id": "a82af0a5-55ed-40c4-b59b-3be76922c24e",
    "name": "The-Gilded-Blight",
    "description": "Mock expansion of the-gilded-blight.md",
    "genre": "Fantasy",
    "difficulty_level": "medium",
    "campaign_length": "full",
    "tone": "epic",
    "setting_details": {},
    "thematic_elements": {
      "mainThemes": [],
      "keyLocations": [],
      "importantNPCs": [],
      "recurringMotifs": []
    }
  },
  "worlds": [
    {
      "id": "881f0ca8-b178-45dd-b6a2-f32287194494",
      "campaign_id": "mock-id",
      "name": "Mock World",
      "description": "Generated during dry run",
      "climate_type": "temperate",
      "magic_level": "standard",
      "technology_level": "medieval"
    }
  ],
  "npcs": [
    {
      "id": "6a0b8584-d5cd-4d15-95d2-5cc0302df64b",
      "world_id": "mock-world-id",
      "name": "Mock NPC",
      "race": "Human",
      "class_": "Fighter",
      "level": 5,
      "description": "Generated NPC",
      "personality": "Brave",
      "stats": {}
    }
  ],
  "quests": [
    {
      "id": "405921d7-c005-475b-bbb4-d4b11c0d7f3b",
      "campaign_id": "mock-id",
      "title": "Mock Quest",
      "description": "Sample quest",
      "difficulty": "medium",
      "quest_type": "main",
      "prerequisites": {},
      "rewards": {}
    }
  ],
  "locations": [
    {
      "id": "cd3b302a-63e4-408c-a2a4-528cd24563fc",
      "world_id": "mock-world-id",
      "name": "Mock Location",
      "location_type": "village",
      "description": "Sample location",
      "parent_location_id": null,
      "coordinates": null
    }
  ],
  "factions": [],
  "history_events": [],
  "memories": []
}